AUTHORS
CHANGELOG
LICENSE
MANIFEST.in
README.md
setup.py
django_mobilvest.egg-info/PKG-INFO
django_mobilvest.egg-info/SOURCES.txt
django_mobilvest.egg-info/dependency_links.txt
django_mobilvest.egg-info/not-zip-safe
django_mobilvest.egg-info/requires.txt
django_mobilvest.egg-info/top_level.txt
mobilvest/__init__.py
mobilvest/__init__.pyc
mobilvest/admin.py
mobilvest/forms.py
mobilvest/models.py
mobilvest/settings.py
mobilvest/tasks.py
mobilvest/tests.py
mobilvest/urls.py
mobilvest/utils.py
mobilvest/views.py
mobilvest/migrations/0001_initial.py
mobilvest/migrations/0002_auto__add_smstemplate__add_smsreport.py
mobilvest/migrations/__init__.py
mobilvest/templates/admin/send_sms.html