Metadata-Version: 1.1
Name: django-mobilvest
Version: 0.1.1
Summary: This Django is a sms-sender backend for http://mobilvest.ru service
Home-page: https://bitbucket.org/ir4y/django-mobilvest
Author: Ilya Beda
Author-email: ir4y.ix@gmail.com
License: UNKNOWN
Platform: UNKNOWN
Classifier: Development Status :: 4 - Beta
Classifier: Environment :: Web Environment
Classifier: Framework :: Django
Classifier: Intended Audience :: Developers
Classifier: License :: OSI Approved :: BSD License
Classifier: Operating System :: OS Independent
Classifier: Programming Language :: Python
